{
  "gamecube_games": [
    {
      "title": "Super Smash Bros. Melee",
      "cover": "super_smash_bros_melee.png",
      "region": "NTSC",
      "languages": ["English", "Spanish", "French"],
      "size": "1.2 GB",
      "link": "https://example.com/super_smash_bros_melee",
      "rating": 9.5,
      "description": "Fighting game with Nintendo characters in fast-paced battles.",
      "console": "GameCube",
      "gameplay_url": "https://youtube.com/gameplay_super_smash_bros_melee",
      "url_download": "https://example.com/download_super_smash_bros_melee"
    },
    {
      "title": "The Legend of Zelda: The Wind Waker",
      "cover": "zelda_wind_waker.png",
      "region": "PAL",
      "languages": ["English", "German", "Italian", "Spanish"],
      "size": "1.4 GB",
      "link": "https://example.com/zelda_wind_waker",
      "rating": 9.2,
      "description": "Epic adventure with Link exploring a vast ocean and rescuing his sister.",
      "console": "GameCube",
      "gameplay_url": "https://youtube.com/gameplay_zelda_wind_waker",
      "url_download": "https://example.com/download_zelda_wind_waker"
    },
    {
      "title": "Metroid Prime",
      "cover": "metroid_prime.png",
      "region": "NTSC",
      "languages": ["English", "French", "Spanish"],
      "size": "1.3 GB",
      "link": "https://example.com/metroid_prime",
      "rating": 9.4,
      "description": "First-person adventure featuring Samus Aran exploring a mysterious planet.",
      "console": "GameCube",
      "gameplay_url": "https://youtube.com/gameplay_metroid_prime",
      "url_download": "https://example.com/download_metroid_prime"
    },
    {
      "title": "Resident Evil 4",
      "cover": "resident_evil_4.png",
      "region": "NTSC",
      "languages": ["English", "Spanish", "French"],
      "size": "1.5 GB",
      "link": "https://example.com/resident_evil_4",
      "rating": 9.6,
      "description": "Survival horror masterpiece with Leon Kennedy battling zombies in Europe.",
      "console": "GameCube",
      "gameplay_url": "https://youtube.com/gameplay_resident_evil_4",
      "url_download": "https://example.com/download_resident_evil_4"
    },
    {
      "title": "Paper Mario: The Thousand-Year Door",
      "cover": "paper_mario_ttyd.png",
      "region": "PAL",
      "languages": ["English", "German", "Spanish", "French"],
      "size": "1.6 GB",
      "link": "https://example.com/paper_mario_ttyd",
      "rating": 9.3,
      "description": "RPG with Mario on a quest to save Princess Peach in a paper-themed world.",
      "console": "GameCube",
      "gameplay_url": "https://youtube.com/gameplay_paper_mario_ttyd",
      "url_download": "https://example.com/download_paper_mario_ttyd"
    },
    {
      "title": "Luigi's Mansion",
      "cover": "luigis_mansion.png",
      "region": "NTSC",
      "languages": ["English", "Spanish", "French"],
      "size": "1.1 GB",
      "link": "https://example.com/luigis_mansion",
      "rating": 9.0,
      "description": "Action-adventure where Luigi explores a haunted mansion to rescue Mario.",
      "console": "GameCube",
      "gameplay_url": "https://youtube.com/gameplay_luigis_mansion",
      "url_download": "https://example.com/download_luigis_mansion"
    },
    {
      "title": "Star Wars: Rogue Squadron II - Rogue Leader",
      "cover": "rogue_squadron_ii.png",
      "region": "PAL",
      "languages": ["English", "German", "Spanish", "French"],
      "size": "1.2 GB",
      "link": "https://example.com/rogue_squadron_ii",
      "rating": 9.1,
      "description": "Arcade-style flight combat set in the Star Wars universe.",
      "console": "GameCube",
      "gameplay_url": "https://youtube.com/gameplay_rogue_squadron_ii",
      "url_download": "https://example.com/download_rogue_squadron_ii"
    },
    {
      "title": "Eternal Darkness: Sanity's Requiem",
      "cover": "eternal_darkness.png",
      "region": "NTSC",
      "languages": ["English", "Spanish", "French"],
      "size": "1.4 GB",
      "link": "https://example.com/eternal_darkness",
      "rating": 9.7,
      "description": "Psychological horror game with a unique sanity mechanic.",
      "console": "GameCube",
      "gameplay_url": "https://youtube.com/gameplay_eternal_darkness",
      "url_download": "https://example.com/download_eternal_darkness"
    },
    {
      "title": "Mario Kart: Double Dash!!",
      "cover": "mario_kart_double_dash.png",
      "region": "NTSC",
      "languages": ["English", "Spanish", "French"],
      "size": "1.2 GB",
      "link": "https://example.com/mario_kart_double_dash",
      "rating": 9.5,
      "description": "Racing game featuring unique double-rider kart mechanics.",
      "console": "GameCube",
      "gameplay_url": "https://youtube.com/gameplay_mario_kart_double_dash",
      "url_download": "https://example.com/download_mario_kart_double_dash"
    },
    {
      "title": "F-Zero GX",
      "cover": "fzero_gx.png",
      "region": "PAL",
      "languages": ["English", "German", "Spanish", "French"],
      "size": "1.3 GB",
      "link": "https://example.com/fzero_gx",
      "rating": 9.4,
      "description": "High-speed futuristic racing with intense tracks and vehicles.",
      "console": "GameCube",
      "gameplay_url": "https://youtube.com/gameplay_fzero_gx",
      "url_download": "https://example.com/download_fzero_gx"
    },
    {
      "title": "Animal Crossing",
      "cover": "animal_crossing.png",
      "region": "NTSC",
      "languages": ["English", "Spanish", "French"],
      "size": "1.1 GB",
      "link": "https://example.com/animal_crossing",
      "rating": 9.0,
      "description": "Life simulation game where players create and manage their own village.",
      "console": "GameCube",
      "gameplay_url": "https://youtube.com/gameplay_animal_crossing",
      "url_download": "https://example.com/download_animal_crossing"
    },
    {
      "title": "Pikmin",
      "cover": "pikmin.png",
      "region": "NTSC",
      "languages": ["English", "Spanish", "French"],
      "size": "1.2 GB",
      "link": "https://example.com/pikmin",
      "rating": 9.2,
      "description": "Strategy game where Captain Olimar commands plant-like creatures to solve puzzles.",
      "console": "GameCube",
      "gameplay_url": "https://youtube.com/gameplay_pikmin",
      "url_download": "https://example.com/download_pikmin"
    },
    {
      "title": "Soulcalibur II",
      "cover": "soulcalibur_ii.png",
      "region": "PAL",
      "languages": ["English", "German", "Spanish", "French"],
      "size": "1.5 GB",
      "link": "https://example.com/soulcalibur_ii",
      "rating": 9.3,
      "description": "Fighting game with a diverse roster of characters and weapon-based combat.",
      "console": "GameCube",
      "gameplay_url": "https://youtube.com/gameplay_soulcalibur_ii",
      "url_download": "https://example.com/download_soulcalibur_ii"
    },
    {
      "title": "Viewtiful Joe",
      "cover": "viewtiful_joe.png",
      "region": "NTSC",
      "languages": ["English", "Spanish", "French"],
      "size": "1.1 GB",
      "link": "https://example.com/viewtiful_joe",
      "rating": 9.4,
      "description": "Stylish beat 'em up with time-manipulating powers and comic book aesthetics.",
      "console": "GameCube",
      "gameplay_url": "https://youtube.com/gameplay_viewtiful_joe",
      "url_download": "https://example.com/download_viewtiful_joe"
    },
    {
      "title": "Tales of Symphonia",
      "cover": "tales_of_symphonia.png",
      "region": "PAL",
      "languages": ["English", "German", "Spanish", "French"],
      "size": "1.6 GB",
      "link": "https://example.com/tales_of_symphonia",
      "rating": 9.5,
      "description": "Japanese RPG with a rich story and engaging real-time combat.",
      "console": "GameCube",
      "gameplay_url": "https://youtube.com/gameplay_tales_of_symphonia",
      "url_download": "https://example.com/download_tales_of_symphonia"
    }
  ]
}
